cli_draw.py
cli_draw-0.0.1.dist-info/LICENSE
cli_draw-0.0.1.dist-info/METADATA
cli_draw-0.0.1.dist-info/WHEEL
cli_draw-0.0.1.dist-info/top_level.txt
cli_draw-0.0.1.dist-info/RECORD
